sgbench/__init__.py
sgbench/__main__.py
sgbench/file.py
sgbench/io.py
sgbench/match.py
sgbench/metrics.py
sgbench/pred.py
sgbench/version.py
sgbench-1.0.0.dist-info/LICENSE
sgbench-1.0.0.dist-info/METADATA
sgbench-1.0.0.dist-info/WHEEL
sgbench-1.0.0.dist-info/entry_points.txt
sgbench-1.0.0.dist-info/RECORD
